pastamarkers/__init__.py
pastamarkers/add_marker.py
pastamarkers/cupboard.py
pastamarkers/markers.pkl
pastamarkers/markers.py
pastamarkers/pasta.pkl
pastamarkers/salsa.pkl
pastamarkers-1.0.2.dist-info/LICENSE
pastamarkers-1.0.2.dist-info/METADATA
pastamarkers-1.0.2.dist-info/WHEEL
pastamarkers-1.0.2.dist-info/RECORD
