Metadata-Version: 2.1
Name: pastamarkers
Version: 1.0.2
Summary: astrophysical data visualization with pasta-like markers
Home-page: https://github.com/LR-inaf/pasta-marker
Author: Luca Rosignoli
Author-email: luca.rosignoli@inaf.it
Requires-Python: >=3.10,<4.0
Classifier: Development Status :: 5 - Production/Stable
Classifier: Intended Audience :: Science/Research
Classifier: License :: OSI Approved :: GNU General Public License v3 or later (GPLv3+)
Classifier: Operating System :: OS Independent
Classifier: Programming Language :: Python :: 3
Classifier: Programming Language :: Python :: 3.10
Classifier: Programming Language :: Python :: 3.11
Classifier: Programming Language :: Python :: 3.12
Classifier: Programming Language :: Python :: 3.8
Classifier: Programming Language :: Python :: 3.9
Classifier: Topic :: Scientific/Engineering :: Astronomy
Classifier: Topic :: Scientific/Engineering :: Visualization
Requires-Dist: matplotlib (>=3.4.3,<4.0.0)
Requires-Dist: numpy (>=2.0.0,<3.0.0)
Requires-Dist: svgpath2mpl (==1.0.0)
Project-URL: Repository, https://github.com/LR-inaf/pasta-marker
